MANIFEST.in
setup.py
sheep/__init__.py
sheep/shepherd.py