Metadata-Version: 1.1
Name: sheep
Version: 0.3.3
Summary: Sheep is a console worker generator.
Home-page: https://github.com/heynemann/sheep
Author: Bernardo Heynemann
Author-email: heynemann@gmail.com
License: MIT
Keywords: worker console
Platform: UNKNOWN
Classifier: Development Status :: 4 - Beta
Classifier: Intended Audience :: Developers
Classifier: License :: OSI Approved :: MIT License
Classifier: Natural Language :: English
Classifier: Operating System :: MacOS
Classifier: Operating System :: POSIX
Classifier: Operating System :: Unix
Classifier: Operating System :: OS Independent
Classifier: Programming Language :: Python :: 2.7
